breaking_point/__init__.py
breaking_point/breaking_point.py
breaking_point-0.1.0.data/data/LICENSE
breaking_point-0.1.0.data/data/README.rst
breaking_point-0.1.0.dist-info/DESCRIPTION.rst
breaking_point-0.1.0.dist-info/METADATA
breaking_point-0.1.0.dist-info/RECORD
breaking_point-0.1.0.dist-info/WHEEL
breaking_point-0.1.0.dist-info/metadata.json
breaking_point-0.1.0.dist-info/top_level.txt
