Metadata-Version: 2.0
Name: breaking-point
Version: 0.1.0
Summary: breaking-point.py helps to find a size of input data where one function starts outperform another function. It is a convenient way to compare different algorithms for a single task.
Home-page: https://github.com/dizballanze/breaking-point
Author: Yuri Shikanov
Author-email: dizballanze@gmail.com
License: MIT
Platform: UNKNOWN
